csv2table/__init__.py
csv2table/csv2table.py
csv2table-0.5.0.dist-info/LICENCE
csv2table-0.5.0.dist-info/METADATA
csv2table-0.5.0.dist-info/WHEEL
csv2table-0.5.0.dist-info/entry_points.txt
csv2table-0.5.0.dist-info/top_level.txt
csv2table-0.5.0.dist-info/RECORD
